Workbook

Sheet Inventory Data
A1: date | B1: product | C1: quantity_kg | D1: unit_price | E1: total_cost | F1: daily_usage_kg | G1: remaining_stock_kg | H1: month
A2: 45566 | B2: Adhesive | C2: 46 | D2: 143 | E2: 6578 | F2: 22 | G2: 24 | H2: 2024-10
A3: 45566 | B3: Silicone | C3: 68 | D3: 236 | E3: 16048 | F3: 19 | G3: 49 | H3: 2024-10
A4: 45566 | B4: Adhesive | C4: 30 | D4: 217 | E4: 6510 | F4: 15 | G4: 15 | H4: 2024-10
A5: 45567 | B5: Silicone | C5: 80 | D5: 293 | E5: 23440 | F5: 1 | G5: 79 | H5: 2024-10
A6: 45567 | B6: Silicone | C6: 62 | D6: 218 | E6: 13516 | F6: 6 | G6: 56 | H6: 2024-10
A7: 45567 | B7: Adhesive | C7: 84 | D7: 221 | E7: 18564 | F7: 32 | G7: 52 | H7: 2024-10
A8: 45567 | B8: Vinyl | C8: 40 | D8: 172 | E8: 6880 | F8: 20 | G8: 20 | H8: 2024-10
A9: 45568 | B9: Adhesive | C9: 67 | D9: 179 | E9: 11993 | F9: 6 | G9: 61 | H9: 2024-10
A10: 45568 | B10: Ink | C10: 58 | D10: 128 | E10: 7424 | F10: 6 | G10: 52 | H10: 2024-10
A11: 45568 | B11: Adhesive | C11: 71 | D11: 110 | E11: 7810 | F11: 15 | G11: 56 | H11: 2024-10
A12: 45569 | B12: Ink | C12: 71 | D12: 233 | E12: 16543 | F12: 15 | G12: 56 | H12: 2024-10
A13: 45569 | B13: Adhesive | C13: 59 | D13: 110 | E13: 6490 | F13: 13 | G13: 46 | H13: 2024-10
... A201: 45657 | B201: Silicone | C201: 36 | D201: 276 | E201: 9936 | F201: 6 | G201: 30 | H201: 2024-12

Sheet ANALYSIS 1
B2: ITEM | C2: SUM OF QUANITITY
B3: ADHESIVE | C3: =SUMIF('Inventory Data'!B2:B201,"Adhesive",'Inventory Data'!C2:C201) -> 3341
B4: VINYL | C4: =SUMIF('Inventory Data'!B2:B201,"Vinyl",'Inventory Data'!C2:C201) -> 2358
B5: SILICONE | C5: =SUMIF('Inventory Data'!B2:B201,"Silicone",'Inventory Data'!C2:C201) -> 2675
B6: INK | C6: =SUMIF('Inventory Data'!B2:B201,"Ink",'Inventory Data'!C2:C201) -> 2999
B19: MONTH | C19: QUANTITY PURCHASED
B20: OCTOBER | C20: =SUMIF('Inventory Data'!H2:H201,"2024-10",'Inventory Data'!C2:C201) -> 4631
B21: NOVEMBER | C21: =SUMIF('Inventory Data'!H2:H201,"2024-11",'Inventory Data'!C2:C201) -> 3240
B22: DECEMBER | C22: =SUMIF('Inventory Data'!H2:H201,"2024-12",'Inventory Data'!C2:C201) -> 3502
A37: INVENTORY TURNOVER | B37: =SUM('Inventory Data'!F2:F201)/((SUM('Inventory Data'!C2:C201)+ SUM('Inventory Data'!G2:G201)/2)) -> 0.18263818 | C37: which means low turnover
C38: calculated by = daily_usage_kg / ((quantity_kg + remaining_stock_kg) / 2)
C41: PRODUCT | D41: OCTOBER | E41: NOVEMBER | F41: DECEMBER
C42: quantity_kg | D42: =SUMIF('Inventory Data'!H2:H201,"2024-10",'Inventory Data'!C2:C201) -> 4631 | E42: 3240 | F42: 3502
C43: AVG daily_usage_kg | D43: =AVERAGE(SUMIF('Inventory Data'!H2:H201,"2024-10",'Inventory Data'!F2:F201)) -> 1217 | E43: =AVERAGE(SUMIF('Inventory Data'!H2:H201,"2024-11",'Inventory Data'!F2:F201)) -> 726 | F43: =AVERAGE(SUMIF('Inventory Data'!H2:H201,"2024-12",'Inventory Data'!F2:F201)) -> 912
C44: AVG remaining_stock_kg | D44: =AVERAGE(SUMIF('Inventory Data'!H2:H201,"2024-10",'Inventory Data'!G2:G201)) -> 3414 | E44: =AVERAGE(SUMIF('Inventory Data'!H2:H201,"2024-11",'Inventory Data'!G2:G201)) -> 2514 | F44: =AVERAGE(SUMIF('Inventory Data'!H2:H201,"2024-12",'Inventory Data'!G2:G201)) -> 2590 | H44: Row Labels | I44: Sum of OCTOBER | J44: Sum of NOVEMBER | K44: Sum of DECEMBER
H45: daily_usage_kg | I45: 1217 | J45: 726 | K45: 912
H46: quantity_kg | I46: 4631 | J46: 3240 | K46: 3502
H47: remaining_stock_kg | I47: 3414 | J47: 2514 | K47: 2590
H48: Grand Total | I48: 9262 | J48: 6480 | K48: 7004

Sheet Sales Data
A1: sale_date | B1: product_type | C1: sticker_name | D1: units_sold | E1: unit_price | F1: cost_price | G1: total_cost | H1: total_revenue | I1: profit | J1: profit_margin_pct
A2: 45566 | B2: Logo Stickers | C2: Ankit | D2: 1500 | E2: 5 | F2: 4 | G2: 6000 | H2: 7500 | I2: 1500 | J2: 20
A3: 45566 | B3: Custom Design Stickers | C3: Car | D3: 2500 | E3: 15 | F3: 5 | G3: 12500 | H3: 37500 | I3: 25000 | J3: 67
A4: 45566 | B4: Cartoon Stickers | C4: Mickey | D4: 1500 | E4: 13 | F4: 3 | G4: 4500 | H4: 19500 | I4: 15000 | J4: 77
A5: 45566 | B5: Custom Design Stickers | C5: Monkey | D5: 500 | E5: 7 | F5: 5 | G5: 2500 | H5: 3500 | I5: 1000 | J5: 29
A6: 45566 | B6: Cartoon Stickers | C6: Doraemon | D6: 1500 | E6: 11 | F6: 5 | G6: 7500 | H6: 16500 | I6: 9000 | J6: 55
A7: 45566 | B7: Logo Stickers | C7: Ankit | D7: 1000 | E7: 7 | F7: 3 | G7: 3000 | H7: 7000 | I7: 4000 | J7: 57
A8: 45567 | B8: Cartoon Stickers | C8: Nobita | D8: 1500 | E8: 18 | F8: 17 | G8: 25500 | H8: 27000 | I8: 1500 | J8: 6
A9: 45567 | B9: Cartoon Stickers | C9: Nobita | D9: 2500 | E9: 15 | F9: 14 | G9: 35000 | H9: 37500 | I9: 2500 | J9: 7
A10: 45567 | B10: Custom Design Stickers | C10: Car | D10: 2500 | E10: 17 | F10: 6 | G10: 15000 | H10: 42500 | I10: 27500 | J10: 65
A11: 45567 | B11: Logo Stickers | C11: Adidas | D11: 1000 | E11: 8 | F11: 4 | G11: 4000 | H11: 8000 | I11: 4000 | J11: 50
A12: 45567 | B12: Custom Design Stickers | C12: Flower | D12: 1500 | E12: 19 | F12: 4 | G12: 6000 | H12: 28500 | I12: 22500 | J12: 79
A13: 45567 | B13: Logo Stickers | C13: Avinash | D13: 2000 | E13: 5 | F13: 3 | G13: 6000 | H13: 10000 | I13: 4000 | J13: 40
... A601: 45657 | B601: Cartoon Stickers | C601: Nobita | D601: 1000 | E601: 20 | F601: 13 | G601: 13000 | H601: 20000 | I601: 7000 | J601: 35

Sheet ANALYSIS 2
B2: Sticker name | C2: SUM OF EACH ORDER | D2: Profit
B3: ankit | C3: =COUNTIF('Sales Data'!C2:C601,"Ankit") -> 40 | D3: =SUMIF('Sales Data'!C2:C601,"Ankit",'Sales Data'!I2:I601) -> 288500
B4: car | C4: =COUNTIF('Sales Data'!C2:C601,"Car") -> 39 | D4: =SUMIF('Sales Data'!C2:C601,"Car",'Sales Data'!I2:I601) -> 401500
B5: monkey | C5: =COUNTIF('Sales Data'!C2:C601,"Monkey") -> 48 | D5: =SUMIF('Sales Data'!C2:C601,"Monkey",'Sales Data'!I2:I601) -> 250000
B6: x | C6: =COUNTIF('Sales Data'!C2:C601,"X") -> 30 | D6: =SUMIF('Sales Data'!C2:C601,"X",'Sales Data'!I2:I601) -> 280000
B7: avinash | C7: =COUNTIF('Sales Data'!C2:C601,"Avinash") -> 38 | D7: =SUMIF('Sales Data'!C2:C601,"Avinash",'Sales Data'!I2:I601) -> 341000
B8: doraemon | C8: =COUNTIF('Sales Data'!C2:C601,"Doraemon") -> 52 | D8: =SUMIF('Sales Data'!C2:C601,"Doraemon",'Sales Data'!I2:I601) -> 434500
B9: perman | C9: =COUNTIF('Sales Data'!C2:C601,"Perman") -> 25 | D9: =SUMIF('Sales Data'!C2:C601,"Perman",'Sales Data'!I2:I601) -> 165500
B10: shinchan | C10: =COUNTIF('Sales Data'!C2:C601,"Shinchan") -> 46 | D10: =SUMIF('Sales Data'!C2:C601,"Shinchan",'Sales Data'!I2:I601) -> 344500
B11: nobita | C11: =COUNTIF('Sales Data'!C2:C601,"Nobita") -> 39 | D11: =SUMIF('Sales Data'!C2:C601,"Nobita",'Sales Data'!I2:I601) -> 164000
B12: flower | C12: =COUNTIF('Sales Data'!C2:C601,"Flower") -> 46 | D12: =SUMIF('Sales Data'!C2:C601,"Flower",'Sales Data'!I2:I601) -> 333500
B13: house | C13: =COUNTIF('Sales Data'!C2:C601,"House") -> 33 | D13: =SUMIF('Sales Data'!C2:C601,"House",'Sales Data'!I2:I601) -> 191000
B14: adidas | C14: =COUNTIF('Sales Data'!C2:C601,"Adidas") -> 42 | D14: =SUMIF('Sales Data'!C2:C601,"Adidas",'Sales Data'!I2:I601) -> 248500
B15: mickey | C15: =COUNTIF('Sales Data'!C2:C601,"Mickey") -> 39 | D15: =SUMIF('Sales Data'!C2:C601,"MIckey",'Sales Data'!I2:I601) -> 258000
B16: nike | C16: =COUNTIF('Sales Data'!C2:C601,"Nike") -> 36 | D16: =SUMIF('Sales Data'!C2:C601,"Nike",'Sales Data'!I2:I601) -> 257000
B17: strawberry | C17: =COUNTIF('Sales Data'!C2:C601,"Strawberry") -> 47 | D17: =SUMIF('Sales Data'!C2:C601,"Strawberry",'Sales Data'!I2:I601) -> 291500
B18: TOTAL | C18: =SUM(C3:C17) -> 600
B22: Product type | C22: total revenue
B23: Cartoon | C23: =SUMIF('Sales Data'!B2:B601,"Cartoon Stickers",'Sales Data'!H2:H601) -> 3264000
B24: Logo | C24: =SUMIF('Sales Data'!B2:B601,"Logo Stickers",'Sales Data'!H2:H601) -> 3437000
B25: custom designs | C25: =SUMIF('Sales Data'!B2:B601,"Custom Design Stickers",'Sales Data'!H2:H601) -> 3484000
B40: Sticker name | C40: Total Revenue | D40: cumulative %
B41: Doraemon | C41: =SUMIF('Sales Data'!C2:C601,"Doraemon",'Sales Data'!H2:H601) -> 938000 | D41: =SUM($C$41:C41)/SUM($C$41:$C$55) -> 0.09209622
B42: Shinchan | C42: =SUMIF('Sales Data'!C2:C601,"Shinchan",'Sales Data'!H2:H601) -> 825500 | D42: =SUM($C$41:C42)/SUM($C$41:$C$55) -> 0.17314678
B43: Car | C43: =SUMIF('Sales Data'!C2:C601,"Car",'Sales Data'!H2:H601) -> 820500 | D43: =SUM($C$41:C43)/SUM($C$41:$C$55) -> 0.25370643
B44: Avinash | C44: =SUMIF('Sales Data'!C2:C601,"Avinash",'Sales Data'!H2:H601) -> 801000 | D44: =SUM($C$41:C44)/SUM($C$41:$C$55) -> 0.3323515
B45: Flower | C45: =SUMIF('Sales Data'!C2:C601,"Flower",'Sales Data'!H2:H601) -> 795500 | D45: =SUM($C$41:C45)/SUM($C$41:$C$55) -> 0.41045655
B46: Adidas | C46: =SUMIF('Sales Data'!C2:C601,"Adidas",'Sales Data'!H2:H601) -> 778500 | D46: =SUM($C$41:C46)/SUM($C$41:$C$55) -> 0.48689249
B47: Ankit | C47: =SUMIF('Sales Data'!C2:C601,"Ankit",'Sales Data'!H2:H601) -> 690500 | D47: =SUM($C$41:C47)/SUM($C$41:$C$55) -> 0.55468827
B48: Strawberry | C48: =SUMIF('Sales Data'!C2:C601,"Strawberry",'Sales Data'!H2:H601) -> 682000 | D48: =SUM($C$41:C48)/SUM($C$41:$C$55) -> 0.62164948
B49: Monkey | C49: =SUMIF('Sales Data'!C2:C601,"Monkey",'Sales Data'!H2:H601) -> 622000 | D49: =SUM($C$41:C49)/SUM($C$41:$C$55) -> 0.68271969
B50: X | C50: =SUMIF('Sales Data'!C2:C601,"X",'Sales Data'!H2:H601) -> 588000 | D50: =SUM($C$41:C50)/SUM($C$41:$C$55) -> 0.74045164
B51: Nike | C51: =SUMIF('Sales Data'!C2:C601,"Nike",'Sales Data'!H2:H601) -> 579000 | D51: =SUM($C$41:C51)/SUM($C$41:$C$55) -> 0.79729995
B52: House | C52: =SUMIF('Sales Data'!C2:C601,"House",'Sales Data'!H2:H601) -> 564000 | D52: =SUM($C$41:C52)/SUM($C$41:$C$55) -> 0.8526755
B53: Mickey | C53: =SUMIF('Sales Data'!C2:C601,"Mickey",'Sales Data'!H2:H601) -> 533000 | D53: =SUM($C$41:C53)/SUM($C$41:$C$55) -> 0.90500736
B54: Nobita | C54: =SUMIF('Sales Data'!C2:C601,"Nobita",'Sales Data'!H2:H601) -> 516000 | D54: =SUM($C$41:C54)/SUM($C$41:$C$55) -> 0.9556701
B55: Perman | C55: =SUMIF('Sales Data'!C2:C601,"Perman",'Sales Data'!H2:H601) -> 451500 | D55: =SUM($C$41:C55)/SUM($C$41:$C$55) -> 1

Sheet Waste Data
A1: month | B1: material_type | C1: total_quantity_purchased | D1: total_waste_kg | E1: waste_percentage | F1: round off values
A2: 2024-10 | B2: Adhesive | C2: 1175 | D2: 96 | E2: =(D2/C2)*100 -> 8.1702128 | F2: 0.08
A3: 2024-10 | B3: Ink | C3: 1529 | D3: 91 | E3: =(D3/C3)*100 -> 5.9516024 | F3: 0.06
A4: 2024-10 | B4: Silicone | C4: 985 | D4: 80 | E4: =(D4/C4)*100 -> 8.1218274 | F4: 0.08
A5: 2024-10 | B5: Vinyl | C5: 942 | D5: 65 | E5: =(D5/C5)*100 -> 6.9002123 | F5: 0.07
A6: 2024-11 | B6: Adhesive | C6: 1121 | D6: 105 | E6: =(D6/C6)*100 -> 9.3666369 | F6: 0.09
A7: 2024-11 | B7: Ink | C7: 642 | D7: 50 | E7: =(D7/C7)*100 -> 7.788162 | F7: 0.07
A8: 2024-11 | B8: Silicone | C8: 1066 | D8: 85 | E8: =(D8/C8)*100 -> 7.9737336 | F8: 0.08
A9: 2024-11 | B9: Vinyl | C9: 411 | D9: 11 | E9: =(D9/C9)*100 -> 2.676399 | F9: 0.02
A10: 2024-12 | B10: Adhesive | C10: 1045 | D10: 92 | E10: =(D10/C10)*100 -> 8.8038278 | F10: 0.09
A11: 2024-12 | B11: Ink | C11: 828 | D11: 67 | E11: =(D11/C11)*100 -> 8.0917874 | F11: 0.08
A12: 2024-12 | B12: Silicone | C12: 624 | D12: 25 | E12: =(D12/C12)*100 -> 4.0064103 | F12: 0.04
A13: 2024-12 | B13: Vinyl | C13: 1005 | D13: 86 | E13: =(D13/C13)*100 -> 8.5572139 | F13: 0.08

Sheet ANALYSIS 3
B2: Material type | C2: Total waste | D2: Waste Percentage
B3: Adhesive | C3: =SUMIF('Waste Data'!B2:B13,"Adhesive",'Waste Data'!D2:D13) -> 293 | D3: =AVERAGEIF('Waste Data'!B2:B13, "Adhesive", 'Waste Data'!E2:E13) -> 8.7802258
B4: Ink | C4: =SUMIF('Waste Data'!B2:B13,"Ink",'Waste Data'!D2:D13) -> 208 | D4: =AVERAGEIF('Waste Data'!B2:B13, "Ink", 'Waste Data'!E2:E13) -> 7.2771839
B5: silicone | C5: =SUMIF('Waste Data'!B2:B13,"Silicone",'Waste Data'!D2:D13) -> 190 | D5: =AVERAGEIF('Waste Data'!B2:B13, "Silicone", 'Waste Data'!E2:E13) -> 6.7006571
B6: Vinyl | C6: =SUMIF('Waste Data'!B2:B13,"vinyl",'Waste Data'!D2:D13) -> 162 | D6: =AVERAGEIF('Waste Data'!B2:B13, "Vinyl", 'Waste Data'!E2:E13) -> 6.0446084
B21: Month | C21: Total waste
B22: october | C22: =SUMIF('Waste Data'!A2:A13,"2024-10",'Waste Data'!D2:D13) -> 332
B23: november | C23: =SUMIF('Waste Data'!A2:A13,"2024-11",'Waste Data'!D2:D13) -> 251
B24: december | C24: =SUMIF('Waste Data'!A2:A13,"2024-12",'Waste Data'!D2:D13) -> 270

Sheet Competitor Data
A1: competitor_name | B1: product_type | C1: period | D1: region | E1: price
A2: LabelX | B2: Cartoon Stickers | C2: 2024-10 | D2: South | E2: 16
A3: LabelX | B3: Logo Stickers | C3: 2024-10 | D3: South | E3: 10
A4: LabelX | B4: Custom Design Stickers | C4: 2024-10 | D4: South | E4: 13
A5: LabelX | B5: Cartoon Stickers | C5: 2024-11 | D5: South | E5: 7
A6: LabelX | B6: Logo Stickers | C6: 2024-11 | D6: South | E6: 17
A7: LabelX | B7: Custom Design Stickers | C7: 2024-11 | D7: South | E7: 9
A8: LabelX | B8: Cartoon Stickers | C8: 2024-12 | D8: South | E8: 10
A9: LabelX | B9: Logo Stickers | C9: 2024-12 | D9: South | E9: 18
A10: LabelX | B10: Custom Design Stickers | C10: 2024-12 | D10: South | E10: 17
A11: FootMark Labels | B11: Cartoon Stickers | C11: 2024-10 | D11: West | E11: 13
A12: FootMark Labels | B12: Logo Stickers | C12: 2024-10 | D12: West | E12: 16
A13: FootMark Labels | B13: Custom Design Stickers | C13: 2024-10 | D13: West | E13: 11
... A23: InstaSticker | B23: Cartoon Stickers | C23: 2024-12 | D23: South | E23: 5

Sheet ANALYSIS 4
C2: competitor name | D2: sticker count
C3: LabelX | D3: =COUNTIF('Competitor Data'!A2:A23,"LabelX") -> 9
C4: FootMark Labels | D4: =COUNTIF('Competitor Data'!A2:A23,"FootMark Labels") -> 7
C5: InstaSticker | D5: =COUNTIF('Competitor Data'!A2:A23,"InstaSticker") -> 6
C14: product type | D14: average price
C15: Cartoon stickers | D15: =AVERAGEIF('Competitor Data'!B2:B23,"Cartoon Stickers",'Competitor Data'!E2:E23) -> 9.75
C16: Logo stickers | D16: =AVERAGEIF('Competitor Data'!B2:B23,"Logo Stickers",'Competitor Data'!E2:E23) -> 14.571429
C17: Custom design stickers | D17: =AVERAGEIF('Competitor Data'!B2:B23,"Custom Design Stickers",'Competitor Data'!E2:E23) -> 13.428571
